expression_calculator/__init__.py
expression_calculator/calculator.py
expression_calculator-0.1.0.dist-info/licenses/LICENCE
expression_calculator-0.1.0.dist-info/METADATA
expression_calculator-0.1.0.dist-info/WHEEL
expression_calculator-0.1.0.dist-info/top_level.txt
expression_calculator-0.1.0.dist-info/RECORD
