Metadata-Version: 2.4
Name: expression_calculator
Version: 0.1.0
Summary: Simple expression calculator with safe evaluation
Author-email: Exityx <gdlasorum@gmail.com>
Project-URL: Homepage, https://github.com/ExityxXx/ExpressionCalculator
Classifier: Programming Language :: Python :: 3
Classifier: License :: OSI Approved :: MIT License
Classifier: Operating System :: OS Independent
Requires-Python: >=3.7
License-File: LICENCE
Dynamic: license-file
